{
  "id": 95,
  "conceptType": "Disease",
  "name": "Subependymal Giant Cell Astrocytoma",
  "mappings": [
    {
      "relation": "broadMatch",
      "coding": {
        "id": "oncotree:ENCG",
        "code": "ENCG",
        "name": "Encapsulated Glioma",
        "system": "https://oncotree.mskcc.org",
        "systemVersion": "oncotree_2025_10_03",
        "iris": [
          "https://oncotree.mskcc.org/?version=oncotree_2025_10_03&field=NAME&search=Encapsulated+Glioma+%28ENCG%29"
        ]
      }
    }
  ],
  "extensions": [
    {
      "name": "solid_tumor",
      "value": true,
      "description": "Boolean value for if this tumor type is categorized as a solid tumor."
    }
  ],
  "primaryCoding": {
    "id": "ncit:C3696",
    "code": "C3696",
    "name": "Subependymal Giant Cell Astrocytoma",
    "system": "https://evsexplore.semantics.cancer.gov",
    "systemVersion": "25.01d",
    "iris": [
      "https://evsexplore.semantics.cancer.gov/evsexplore/concept/ncit/C3696"
    ]
  }
}