{
  "id": "doc:ema.vitrakvi",
  "type": "Document",
  "documentType": "Regulatory approval",
  "name": "Vitrakvi (larotrectinib) [product information]. EMA.",
  "title": null,
  "aliases": [],
  "description": "Bayer AG. Vitrakvi (larotrectinib) [product information]. European Medicines Agency website. https://www.ema.europa.eu/en/documents/product-information/vitrakvi-epar-product-information_en.pdf. Revised September 2023. Accessed March 25, 2024.",
  "urls": [
    "https://www.ema.europa.eu/en/documents/product-information/vitrakvi-epar-product-information_en.pdf",
    "https://www.ema.europa.eu/en/medicines/human/EPAR/vitrakvi"
  ],
  "doi": null,
  "pmid": null,
  "extensions": [
    {
      "name": "agent",
      "value": {
        "id": "ema",
        "type": "Agent",
        "agentType": "organization",
        "name": "European Medicines Agency",
        "description": "Regulatory agency that approves medicines for use in the European Union.",
        "extensions": [
          {
            "name": "last_updated",
            "value": "2025-10-01",
            "description": ""
          },
          {
            "name": "url",
            "value": "https://www.ema.europa.eu/en/medicines",
            "description": ""
          }
        ]
      },
      "description": "The organization that published this document."
    },
    {
      "name": "application_number",
      "value": null,
      "description": "Biologic License Application (BLA) number, only applicable to documents from the US FDA."
    },
    {
      "name": "company",
      "value": "Bayer AG.",
      "description": "The company that manufactures the cancer drug. Only applicable to market authorization documents."
    },
    {
      "name": "drug_name_brand",
      "value": "Vitrakvi",
      "description": "The brand name of the cancer drug, per this document. Only applicable to market authorization documents."
    },
    {
      "name": "drug_name_generic",
      "value": "larotrectinib",
      "description": "The generic name of the cancer drug, per this document. Only applicable to market authorization documents."
    },
    {
      "name": "first_publication_date",
      "value": "2019-10-24",
      "description": "The publication date for the initial version of this document."
    },
    {
      "name": "publication_date",
      "value": "2023-09-22",
      "description": "The publication date for the document."
    },
    {
      "name": "status",
      "value": "Active",
      "description": "Whether this document is Active or Deprecated within moalmanac-db."
    }
  ]
}