{
  "id": 373,
  "type": "Statement",
  "description": "The U.S. Food and Drug Administration granted approval to pembrolizumab for the treatment of adult and pediatric patients with unresectable or metastatic microsatellite instability-high (MSI-H) or mismatch repair deficient (dMMR) solid tumors, as determined by an FDA approved test, that have progressed following prior treatment and who have no satisfactory alternative treatment options.",
  "contributions": [
    {
      "id": 0,
      "type": "Contribution",
      "description": "Initial access of FDA approvals",
      "date": "2024-10-30",
      "contributor": {
        "id": "vanallenlab",
        "type": "Agent",
        "agentType": "contributor",
        "name": "Van Allen lab",
        "description": "Van Allen lab, Dana-Farber Cancer Institute"
      }
    }
  ],
  "reportedIn": [
    {
      "id": "doc:fda.keytruda",
      "type": "Document",
      "documentType": "Regulatory approval",
      "name": "Keytruda (pembrolizumab) [package insert]. FDA.",
      "title": null,
      "aliases": [],
      "description": "Merck Sharp & Dohme Corp. Keytruda (pembrolizumab) [package insert]. U.S. Food and Drug Administration website. https://www.accessdata.fda.gov/drugsatfda_docs/label/2026/125514Orig1s186lbl.pdf. Revised February 2026. Accessed March 2, 2026.",
      "urls": [
        "https://www.accessdata.fda.gov/drugsatfda_docs/label/2026/125514Orig1s186lbl.pdf",
        "https://www.accessdata.fda.gov/scripts/cder/daf/index.cfm?event=overview.process&ApplNo=125514"
      ],
      "doi": null,
      "pmid": null,
      "extensions": [
        {
          "name": "agent",
          "value": {
            "id": "fda",
            "type": "Agent",
            "agentType": "organization",
            "name": "Food and Drug Administration",
            "description": "Regulatory agency that approves drugs for use in the United States."
          },
          "description": "The organization that published this document."
        },
        {
          "name": "company",
          "value": "Merck Sharp & Dohme Corp.",
          "description": "The company that manufactures the cancer drug. Only applicable to market authorization documents."
        },
        {
          "name": "drug_name_brand",
          "value": "Keytruda",
          "description": "The brand name of the cancer drug, per this document. Only applicable to market authorization documents."
        },
        {
          "name": "drug_name_generic",
          "value": "pembrolizumab",
          "description": "The generic name of the cancer drug, per this document. Only applicable to market authorization documents."
        },
        {
          "name": "first_publication_date",
          "value": "2014-09-04",
          "description": "The publication date for the initial version of this document."
        },
        {
          "name": "identification_number",
          "value": 125514,
          "description": "Identification number used by the publishing organization."
        },
        {
          "name": "publication_date",
          "value": "2026-02-10",
          "description": "The publication date for the document."
        },
        {
          "name": "status",
          "value": "Active",
          "description": "Whether this document is Active or Deprecated within moalmanac-db."
        }
      ]
    }
  ],
  "direction": "supports",
  "indication": {
    "id": "ind:fda.keytruda:4",
    "indication": "KEYTRUDA is a programmed death receptor-1 (PD-1)-blocking antibody indicated for the treatment of adult and pediatric patients with unresectable or metastatic microsatellite instability-high (MSI-H) or mismatch repair deficient (dMMR) solid tumors, as determined by an FDA approved test, that have progressed following prior treatment and who have no satisfactory alternative treatment options.",
    "initial_approval_date": null,
    "initial_approval_url": null,
    "description": "The U.S. Food and Drug Administration granted approval to pembrolizumab for the treatment of adult and pediatric patients with unresectable or metastatic microsatellite instability-high (MSI-H) or mismatch repair deficient (dMMR) solid tumors, as determined by an FDA approved test, that have progressed following prior treatment and who have no satisfactory alternative treatment options.",
    "raw_biomarkers": "MSI-H or dMMR",
    "raw_cancer_type": "unresectable or metastatic ... solid tumors",
    "raw_therapeutics": "Keytruda (pembrolizumab)",
    "document": {
      "id": "doc:fda.keytruda",
      "type": "Document",
      "documentType": "Regulatory approval",
      "name": "Keytruda (pembrolizumab) [package insert]. FDA.",
      "title": null,
      "aliases": [],
      "description": "Merck Sharp & Dohme Corp. Keytruda (pembrolizumab) [package insert]. U.S. Food and Drug Administration website. https://www.accessdata.fda.gov/drugsatfda_docs/label/2026/125514Orig1s186lbl.pdf. Revised February 2026. Accessed March 2, 2026.",
      "urls": [
        "https://www.accessdata.fda.gov/drugsatfda_docs/label/2026/125514Orig1s186lbl.pdf",
        "https://www.accessdata.fda.gov/scripts/cder/daf/index.cfm?event=overview.process&ApplNo=125514"
      ],
      "doi": null,
      "pmid": null,
      "extensions": [
        {
          "name": "agent",
          "value": {
            "id": "fda",
            "type": "Agent",
            "agentType": "organization",
            "name": "Food and Drug Administration",
            "description": "Regulatory agency that approves drugs for use in the United States."
          },
          "description": "The organization that published this document."
        },
        {
          "name": "company",
          "value": "Merck Sharp & Dohme Corp.",
          "description": "The company that manufactures the cancer drug. Only applicable to market authorization documents."
        },
        {
          "name": "drug_name_brand",
          "value": "Keytruda",
          "description": "The brand name of the cancer drug, per this document. Only applicable to market authorization documents."
        },
        {
          "name": "drug_name_generic",
          "value": "pembrolizumab",
          "description": "The generic name of the cancer drug, per this document. Only applicable to market authorization documents."
        },
        {
          "name": "first_publication_date",
          "value": "2014-09-04",
          "description": "The publication date for the initial version of this document."
        },
        {
          "name": "identification_number",
          "value": 125514,
          "description": "Identification number used by the publishing organization."
        },
        {
          "name": "publication_date",
          "value": "2026-02-10",
          "description": "The publication date for the document."
        },
        {
          "name": "status",
          "value": "Active",
          "description": "Whether this document is Active or Deprecated within moalmanac-db."
        }
      ]
    }
  },
  "proposition": {
    "id": 322,
    "type": "VariantTherapeuticResponseProposition",
    "predicate": "predictSensitivityTo",
    "biomarkers": [
      {
        "id": 38,
        "type": "CategoricalVariant",
        "name": "MSI-H",
        "extensions": [
          {
            "name": "biomarker_type",
            "value": "Microsatellite Stability"
          },
          {
            "name": "status",
            "value": "Microsatellite instability-high (MSI-H)"
          },
          {
            "name": "_present",
            "value": true
          }
        ]
      }
    ],
    "subjectVariant": {},
    "conditionQualifier": {
      "id": 5,
      "conceptType": "Disease",
      "name": "Any solid tumor",
      "mappings": [],
      "extensions": [
        {
          "name": "solid_tumor",
          "value": true,
          "description": "Boolean value for if this tumor type is categorized as a solid tumor."
        }
      ],
      "primaryCoding": {
        "id": "ncit:C132146",
        "code": "C132146",
        "name": "Malignant Solid Neoplasm",
        "system": "https://evsexplore.semantics.cancer.gov",
        "systemVersion": "25.01d",
        "iris": [
          "https://evsexplore.semantics.cancer.gov/evsexplore/concept/ncit/C132146"
        ]
      }
    },
    "objectTherapeutic": {
      "id": 48,
      "conceptType": "Drug",
      "name": "Pembrolizumab",
      "mappings": [
        {
          "relation": "relatedMatch",
          "coding": {
            "id": "omop:45775965",
            "code": "45775965",
            "name": "pembrolizumab",
            "system": "OMOP",
            "systemVersion": "v20260227",
            "iris": [
              "https://athena.ohdsi.org/search-terms/terms/45775965"
            ]
          }
        },
        {
          "relation": "relatedMatch",
          "coding": {
            "id": "rxcui:1547545",
            "code": "1547545",
            "name": "pembrolizumab",
            "system": "RxNorm",
            "systemVersion": "02-Mar-2026",
            "iris": [
              "https://mor.nlm.nih.gov/RxNav/search?searchBy=RXCUI&searchTerm=1547545"
            ]
          }
        },
        {
          "relation": "relatedMatch",
          "coding": {
            "id": "omop:37396350",
            "code": "37396350",
            "name": "Pembrolizumab",
            "system": "OMOP",
            "systemVersion": "v20260227",
            "iris": [
              "https://athena.ohdsi.org/search-terms/terms/37396350"
            ]
          }
        },
        {
          "relation": "relatedMatch",
          "coding": {
            "id": "sctid:716125002",
            "code": "716125002",
            "name": "Pembrolizumab",
            "system": "SNOMED",
            "systemVersion": "2025-03-01",
            "iris": [
              "https://browser.ihtsdotools.org/?perspective=full&conceptId1=716125002&edition=MAIN/2025-03-01&release=&languages=en"
            ]
          }
        }
      ],
      "extensions": [
        {
          "name": "therapy_strategy",
          "value": [
            "PD-1/PD-L1 inhibition"
          ],
          "description": "Associated therapeutic strategy or mechanism of action of the therapy."
        },
        {
          "name": "therapy_type",
          "value": "Immunotherapy",
          "description": "Type of cancer treatment from cancer.gov: https://www.cancer.gov/about-cancer/treatment/types"
        }
      ],
      "primaryCoding": {
        "id": "ncit:C106432",
        "code": "C106432",
        "name": "Pembrolizumab",
        "system": "https://evsexplore.semantics.cancer.gov",
        "systemVersion": "25.01d",
        "iris": [
          "https://evsexplore.semantics.cancer.gov/evsexplore/concept/ncit/C106432"
        ]
      }
    }
  },
  "strength": {
    "id": 0,
    "conceptType": "Evidence",
    "name": "Approval",
    "mappings": [],
    "primaryCoding": {
      "id": "ncit:C25425",
      "code": "C25425",
      "name": "Approval",
      "system": "https://evsexplore.semantics.cancer.gov",
      "systemVersion": "25.01d",
      "iris": [
        "https://evsexplore.semantics.cancer.gov/evsexplore/concept/ncit/C25425"
      ]
    }
  }
}